aiowebdav/__init__.py
aiowebdav/client.py
aiowebdav/connection.py
aiowebdav/exceptions.py
aiowebdav/typing.py
aiowebdav/urn.py
aiowebdav-0.1.0rc5.data/scripts/wdc
aiowebdav-0.1.0rc5.dist-info/LICENSE.md
aiowebdav-0.1.0rc5.dist-info/METADATA
aiowebdav-0.1.0rc5.dist-info/WHEEL
aiowebdav-0.1.0rc5.dist-info/top_level.txt
aiowebdav-0.1.0rc5.dist-info/RECORD
