Metadata-Version: 2.1
Name: aiowebdav
Version: 0.1.0rc5
Summary: Asyncio WebDAV client, based on original package https://github.com/ezhov-evgeny/webdav-client-python-3 but uses aiohttp instead of requests
Home-page: https://github.com/synodriver/aiowebdav
Author: synodriver
Author-email: diguohuangjiajinweijun@gmail.com
License: MIT License
Keywords: webdav,client,python,module,library,packet,Yandex.Disk,Dropbox,Google Disk,Box,4shared
Classifier: Environment :: Console
Classifier: Environment :: Web Environment
Classifier: License :: OSI Approved :: MIT License
Classifier: Operating System :: MacOS
Classifier: Operating System :: Microsoft
Classifier: Operating System :: Unix
Classifier: Programming Language :: Python :: 3.8
Classifier: Programming Language :: Python :: 3.9
Classifier: Programming Language :: Python :: 3.10
Classifier: Topic :: Internet
Classifier: Topic :: Software Development :: Libraries :: Python Modules
Requires: python (>= 3.8.0)
Requires-Python: >=3.8
License-File: LICENSE.md
Requires-Dist: aiohttp
Requires-Dist: lxml
Requires-Dist: python-dateutil
Requires-Dist: aiofiles
